car_speed_cntl/car_speed_cntl.v
module car_speed_cntl (clock, keys, brake, accelerate, speed);
  input clock, keys, brake, accelerate;
  output [1:0] speed;
  reg[1:0] speed, newspeed;
  parameter STOP = 2'b00, SLOW = 2'b01, 
            MEDIUM = 2'b10, FAST = 2'b11;
  
  always @(posedge clock or negedge keys)
  begin
    if (!keys)
      speed <= STOP;
    else
      speed <= newspeed;
  end
  
  always @(speed or keys or brake or accelerate)
  begin
    case (speed)
      STOP: begin
        if (accelerate)
          newspeed = SLOW;
        else
          newspeed = STOP;
      end
      SLOW: begin
        if (brake) 
          newspeed = STOP;
        else if (accelerate)
          newspeed = MEDIUM;
        else
          newspeed = SLOW;
      end
      MEDIUM: begin
        if (brake) 
          newspeed = SLOW;
        else if (accelerate)
          newspeed = FAST;
        else
          newspeed = MEDIUM;
      end
      FAST: begin
        if (brake) 
          newspeed = MEDIUM;
        else
          newspeed = FAST;
      end
      default: 
        newspeed = STOP;
    endcase
  end
  
endmodule

car_speed_cntl/car_speed_cntl_tb.v
`timescale 1 ns / 10 ps

module main;
  reg clock, keys, brake, accelerate;
  wire [1:0] speed;

  car_speed_cntl test ( 
    .clock(clock),
    .keys(keys),
    .brake(brake),
    .accelerate(accelerate),
    .speed(speed)
  );
  
  // Test clock generation.
  //
  // Clock pulse starts from 0.
  initial 
    clock = 1'b0;
  // Free-running clock  
  always
    #25 clock = ~clock;
    
  // Data stimulus
  initial 
  begin
    #10 keys = 1'b0; brake = 1'b0; accelerate = 1'b0;
    #50 keys = 1'b1;
    #50 accelerate = 1'b1;
    #50 accelerate = 1'b1;
    #50 brake = 1'b1; 
    #50 brake = 1'b1; accelerate = 1'b1;
    #50 brake = 1'b0; accelerate = 1'b1;
    #50 accelerate = 1'b0;
    #50 accelerate = 1'b1;
    #150 brake = 1'b1; accelerate = 1'b0;
    #250
//    $stop;    // for Modelsim
    $finish;  // for Icarus Verilog 
  end

  // Write simulation data to a Value Change Dump (VCD) file.
  // More on this in lecture 07, scheduled next week!
  initial 
  begin
    // Open a VCD file for writing
    $dumpfile("car_speed_cntl.vcd");
    // Dump the values of all nets and wires in module "main", since simulation 
    // time 0
    $dumpvars(0, main);
  end

endmodule

car_speed_cntl/car_speed_cntl.vcd
$date
	Sat Feb 27 22:31:49 2016
$end
$version
	Icarus Verilog
$end
$timescale
	10ps
$end
$scope module main $end
$var wire 2 ! speed [1:0] $end
$var reg 1 " accelerate $end
$var reg 1 # brake $end
$var reg 1 $ clock $end
$var reg 1 % keys $end
$scope module test $end
$var wire 1 & accelerate $end
$var wire 1 ' brake $end
$var wire 1 ( clock $end
$var wire 1 ) keys $end
$var reg 2 * newspeed [1:0] $end
$var reg 2 + speed [1:0] $end
$upscope $end
$upscope $end
$enddefinitions $end
#0
$dumpvars
bx +
bx *
x)
0(
x'
x&
x%
0$
x#
x"
bx !
$end
#1000
b0 +
b0 !
b0 *
0"
0&
0#
0'
0%
0)
#2500
1$
1(
#5000
0$
0(
#6000
1%
1)
#7500
1$
1(
#10000
0$
0(
#11000
b1 *
1"
1&
#12500
b10 *
b1 +
b1 !
1$
1(
#15000
0$
0(
#17500
b11 *
b10 +
b10 !
1$
1(
#20000
0$
0(
#21000
b1 *
1#
1'
#22500
b0 *
b1 +
b1 !
1$
1(
#25000
0$
0(
#27500
b1 *
b0 +
b0 !
1$
1(
#30000
0$
0(
#31000
0#
0'
#32500
b10 *
b1 +
b1 !
1$
1(
#35000
0$
0(
#36000
b1 *
0"
0&
#37500
1$
1(
#40000
0$
0(
#41000
b10 *
1"
1&
#42500
b11 *
b10 +
b10 !
1$
1(
#45000
0$
0(
#47500
b11 +
b11 !
1$
1(
#50000
0$
0(
#52500
1$
1(
#55000
0$
0(
#56000
b10 *
0"
0&
1#
1'
#57500
b1 *
b10 +
b10 !
1$
1(
#60000
0$
0(
#62500
b0 *
b1 +
b1 !
1$
1(
#65000
0$
0(
#67500
b0 +
b0 !
1$
1(
