countbits/countbits_opt.v
// http://noasic.com/blog/move-those-conditions-out-of-those-loops/

module countbits (clk, data, ones);
//  parameter DATA_WIDTH  = 4;
  parameter DATA_WIDTH  = 32;
  input        clk; 
  input  [DATA_WIDTH - 1:0] data; 
  output [2:0] ones; 
  reg    [2:0] ones;
  reg    [2:0] v_count; 
  integer      i;

  always @(posedge clk)
  begin : COUNT_BITS
    v_count = 0; 
    for (i = 0; i <= DATA_WIDTH - 1; i = i + 1)
    begin
      v_count = v_count + data[i]; 
    end
    ones <= v_count;  
  end 
endmodule

countbits/countbits_tb.v
`timescale 1 ns / 1 ns

module countbits_tb;
  parameter DATA_WIDTH  = 4;
  parameter CLK_PERIOD  = 10/*ns*/;
  reg       clk; 
  reg  [DATA_WIDTH - 1:0]     data; 
  wire [$clog2(DATA_WIDTH):0] ones; 
  integer   i;

  countbits uut(
    .clk(clk), 
    .data(data),
    .ones(ones)
  );

  // Test clock generation.
  //
  // Clock pulse starts from 0.
  initial
  begin
    clk   = 1'b0;
  end
  // Free-running clock.
  always
    #(CLK_PERIOD/2) clk = ~clk;
    
  initial 
  begin
    for (i = 0;  i <= (1<<DATA_WIDTH)-1; i = i + 1) 
    begin
      data = i;
      // Apply a 10-time unit delay; think of it as the system machine cycle.
      #(CLK_PERIOD);
      // Display results after 10 time units $.
      $display("%t: data=%h, ones=%d", $time, data, ones);
    end 
    // Automatic end of the current simulation.
    #(CLK_PERIOD);
    $display("End simulation time reached.");
    $finish;
  end

  // Write simulation data to a VCD waveform file.
  initial
  begin
    $dumpfile("countbits.vcd");
    $dumpvars(0, countbits_tb);
  end
  
endmodule // main

countbits/countbits.vcd
$date
	Sat Feb 27 22:31:49 2016
$end
$version
	Icarus Verilog
$end
$timescale
	1ns
$end
$scope module countbits_tb $end
$var wire 3 ! ones [2:0] $end
$var reg 1 " clk $end
$var reg 4 # data [3:0] $end
$var integer 32 $ i [31:0] $end
$scope module uut $end
$var wire 1 % clk $end
$var wire 32 & data [31:0] $end
$var integer 32 ' i [31:0] $end
$var reg 3 ( ones [2:0] $end
$var reg 3 ) v_count [2:0] $end
$scope begin COUNT_BITS $end
$upscope $end
$upscope $end
$upscope $end
$enddefinitions $end
#0
$dumpvars
bx )
bx (
bx '
b0 &
0%
b0 $
b0 #
0"
bx !
$end
#5
b0 (
b0 !
b100000 '
b0 )
1"
1%
#10
0"
0%
b1 #
b1 &
b1 $
#15
b1 (
b1 !
b1 )
b100000 '
1"
1%
#20
0"
0%
b10 #
b10 &
b10 $
#25
b100000 '
b1 )
1"
1%
#30
0"
0%
b11 #
b11 &
b11 $
#35
b10 (
b10 !
b100000 '
b10 )
1"
1%
#40
0"
0%
b100 #
b100 &
b100 $
#45
b1 (
b1 !
b100000 '
b1 )
1"
1%
#50
0"
0%
b101 #
b101 &
b101 $
#55
b10 (
b10 !
b100000 '
b10 )
1"
1%
#60
0"
0%
b110 #
b110 &
b110 $
#65
b100000 '
b10 )
1"
1%
#70
0"
0%
b111 #
b111 &
b111 $
#75
b11 (
b11 !
b100000 '
b11 )
1"
1%
#80
0"
0%
b1000 #
b1000 &
b1000 $
#85
b1 (
b1 !
b100000 '
b1 )
1"
1%
#90
0"
0%
b1001 #
b1001 &
b1001 $
#95
b10 (
b10 !
b100000 '
b10 )
1"
1%
#100
0"
0%
b1010 #
b1010 &
b1010 $
#105
b100000 '
b10 )
1"
1%
#110
0"
0%
b1011 #
b1011 &
b1011 $
#115
b11 (
b11 !
b100000 '
b11 )
1"
1%
#120
0"
0%
b1100 #
b1100 &
b1100 $
#125
b10 (
b10 !
b100000 '
b10 )
1"
1%
#130
0"
0%
b1101 #
b1101 &
b1101 $
#135
b11 (
b11 !
b100000 '
b11 )
1"
1%
#140
0"
0%
b1110 #
b1110 &
b1110 $
#145
b100000 '
b11 )
1"
1%
#150
0"
0%
b1111 #
b1111 &
b1111 $
#155
b100 (
b100 !
b100000 '
b100 )
1"
1%
#160
0"
0%
b10000 $
#165
b100000 '
b100 )
1"
1%
