ram/ram.v
module ram (clk, we, rwaddr, di, do);
  input  clk;
  input  we;
  input  [5:0] rwaddr;
  input  [15:0] di;
  output [15:0] do;
  reg    [15:0] RAM [63:0];
  reg    [15:0] do;

  always @(posedge clk) begin
    if (we)
    begin
      RAM[rwaddr] <= di;
    end
    do <= RAM[rwaddr];    
  end

endmodule

ram/ram_tb.v
`timescale 1 ns / 10 ps

module main;
  reg clk, we;
  reg [5:0] rwaddr;
  reg [15:0] di;
  wire [15:0] do;
  
  ram uut ( 
    .clk(clk),
    .we(we),
    .rwaddr(rwaddr),
    .di(di),
    .do(do)
  );
  
  // Test clock generation.
  //
  // Clock pulse starts from 1.
  initial 
    clk = 1'b1;
  // Free-running clock  
  always
    #25 clk = ~clk;
    
  // Data stimulus
  initial 
  begin
    #1  we = 1'b0; rwaddr = 6'h2A; di = 16'hCAFE;
    #50 we = 1'b1; rwaddr = 6'h2A; di = 16'hCAFE;
    #50 we = 1'b0; rwaddr = 6'h2A; di = 16'hCAFE;
    #50 we = 1'b0; rwaddr = 6'h3A; di = 16'hDEED;
    #50 we = 1'b0; rwaddr = 6'h3A; di = 16'hDEED;
    #50 we = 1'b0; rwaddr = 6'h3A; di = 16'hDEED;
    #50 we = 1'b0; rwaddr = 6'h2A; di = 16'hCAFE;
    #50 we = 1'b1; rwaddr = 6'h2A; di = 16'hCAFE;
    #50
//    $stop;    // for Modelsim
    $finish;  // for Icarus Verilog 
  end
  
  initial
    $monitor("%t: clk = %b, we=%b, rwaddr=%h, di=%h, do=%h", 
    $time, clk, we, rwaddr, di, do);

  // Write simulation data to a Value Change Dump (VCD) file.
  initial 
  begin
    // Open a VCD file for writing
    $dumpfile("ram.vcd");
    // Dump the values of all nets and wires in module "main", since simulation 
    // time 0
    $dumpvars(0, main);
  end

endmodule

ram/ram.vcd
$date
	Sat Feb 27 22:31:50 2016
$end
$version
	Icarus Verilog
$end
$timescale
	10ps
$end
$scope module main $end
$var wire 16 ! do [15:0] $end
$var reg 1 " clk $end
$var reg 16 # di [15:0] $end
$var reg 6 $ rwaddr [5:0] $end
$var reg 1 % we $end
$scope module uut $end
$var wire 1 & clk $end
$var wire 16 ' di [15:0] $end
$var wire 6 ( rwaddr [5:0] $end
$var wire 1 ) we $end
$var reg 16 * do [15:0] $end
$upscope $end
$upscope $end
$enddefinitions $end
#0
$dumpvars
bx *
x)
bx (
bx '
1&
x%
bx $
bx #
1"
bx !
$end
#100
b1100101011111110 #
b1100101011111110 '
b101010 $
b101010 (
0%
0)
#2500
0"
0&
#5000
1"
1&
#5100
1%
1)
#7500
0"
0&
#10000
1"
1&
#10100
0%
0)
#12500
0"
0&
#15000
b1100101011111110 *
b1100101011111110 !
1"
1&
#15100
b1101111011101101 #
b1101111011101101 '
b111010 $
b111010 (
#17500
0"
0&
#20000
bx *
bx !
1"
1&
#22500
0"
0&
#25000
1"
1&
#27500
0"
0&
#30000
1"
1&
#30100
b1100101011111110 #
b1100101011111110 '
b101010 $
b101010 (
#32500
0"
0&
#35000
b1100101011111110 *
b1100101011111110 !
1"
1&
#35100
1%
1)
