mu0/vreg16.v
/**
	project MU0
	module vreg16, 16 bit register
	G. Borg
	Feb 2009
**/
`timescale 1 ns/1 ps
module vreg16 (clk, q, d, en, rs);
`include "defs.h"
  output [MAXWIDTH-1:0] q;
  input  [MAXWIDTH-1:0] d;
  input  clk;
  input  en;
  input  rs;
  reg    [MAXWIDTH-1:0] q;

  always @(posedge clk) 
  begin
    if (en && ~rs) 
      q <= d;
    if (en && rs) 
      q <= 16'h0;
  end

endmodule // v_reg16

mu0/mux12.v
/**
	project MU0
	module mux12, 12 bit mux
	G. Borg
	Feb 2009
**/
`timescale 1 ns/1 ps
module mux12 (z, s, a, b);
`include "defs.h"
  output [MAXDEPTH-1:0] z;
  input  [MAXDEPTH-1:0] a, b;
  input  s;

  assign  z =  s ? b : a ;    // s=1, z<-b; s=0, z<-a

endmodule //mux12.v

mu0/mux16.v
/**
	project MU0
	module mux16, 16 bit mux
	G. Borg
	Feb 2009
**/
`timescale 1 ns/1 ps
module mux16 (z, s, a, b);
`include "defs.h"
  output [MAXWIDTH-1:0] z;
  input  [MAXWIDTH-1:0] a, b;
  input  s;

  assign  z =  s ? b : a ;    // s=1, z<-b; s=0, z<-a

endmodule //mux16.v

mu0/alu16.v
/**
	project MU0
	module alu3_project, 16 bit ALU
	G. Borg
	Feb 2009
**/
`timescale 1 ns/1 ps
module alu16(M, X, Y, Z);
 `include "defs.h"
  parameter Acc = 2'b00; //Pass through to the Accumulator
  parameter Add = 2'b01; //Add X and Y
  parameter PCi = 2'b10; //Increment the Program counter
  parameter Sub = 2'b11; //Subtract Y from X
  input  [1:0] M;
  input  [MAXWIDTH-1:0] X;
  input  [MAXWIDTH-1:0] Y;
  output [MAXWIDTH-1:0] Z;
  reg    [MAXWIDTH-1:0] Z;

  always @(M, X, Y)
  begin
    case(M)
      Add: Z = X + Y;
      Sub: Z = X + ~Y + 1;
      PCi: Z = X + 1;
      Acc: Z = Y;
      default: Z = 0;
    endcase
  end

endmodule //alu16.v

mu0/mu0_datapath.v
/**
	project MU0
	module mu0_ctrl, MU0 Controller
	G. Borg
	Feb 2009
**/
`timescale 1 ns/1 ps
module mu0_datapath(clk, reset, 
  Abus, Xbus, Dbus, acc, ir, pc, 
  M, PCen, IRen, ACCen, Xsel, Ysel, Asel);
`include "defs.h"
  input  clk, reset;
  input  Xsel, Ysel, Asel, ACCen, PCen, IRen;
  input  [1:0] M;
  output [MAXWIDTH-1:0] acc;
  output [MAXWIDTH-1:0] ir;
  output [MAXWIDTH-1:0] pc;
  output [MAXDEPTH-1:0] Abus; // Address bus
  output [MAXWIDTH-1:0] Xbus;
  output [MAXWIDTH-1:0] Dbus; // Data input to MU0
  wire   [MAXWIDTH-1:0] Ybus;
  wire   [MAXWIDTH-1:0] Zbus; // ALU output

  /**********Module instantiations***********************/
  alu16 alu (
    .M(M), .X(Xbus), .Y(Ybus), .Z(Zbus)
  );

  mux16 x_mux (
    .z(Xbus), .s(Xsel), .a(pc), .b(acc)
  );
  mux16 y_mux (
    .z(Ybus), .s(Ysel), .a(ir), .b(Dbus)
  );
  mux12 a_mux (
    .z(Abus), .s(Asel), 
    .a(pc[MAXDEPTH-1:0]), .b(ir[MAXDEPTH-1:0])
  );

  vreg16 ProgramCounter (
    .clk(clk), .q(pc),  .d(Zbus), .en(PCen), .rs(reset)
  );
  vreg16 InstructionRegister (
    .clk(clk), .q(ir),  .d(Dbus), .en(IRen), .rs(reset)
  );
  vreg16 Accumulator (
    .clk(clk), .q(acc), .d(Zbus), .en(ACCen), .rs(reset)
  );

endmodule //mu0_datapath

mu0/mu0_controller.v
/**
	project MU0
	module mu0_ctrl, MU0 Controller
	G. Borg
	Feb 2009
**/
`timescale 1 ns/1 ps
module mu0_controller(clk, reset, opcode, acc, Asel, ACCen,
  PCen, IRen, M, Xsel, Ysel, Ren, Wen);
`include "defs.h"
  input clk;
  input reset;
  input [3:0] opcode;
  input [MAXWIDTH-1:0] acc;
  output Asel, ACCen, PCen, IRen, Xsel, Ysel, Ren, Wen;
  output [1:0] M;
  reg    Asel, ACCen, PCen, IRen, Xsel, Ysel, Ren, Wen;
  reg    [1:0] M;
  reg    [1:0] state, next_state;
  parameter INIT  = 2'b00;
  parameter FETCH = 2'b01;
  parameter EXEC  = 2'b10;
  // In the following S = last 12 bits of the IR, which is an address in memory
  reg [3:0] LDA = 4'b0000;  //Load the contents of S into ACC
  reg [3:0] STO = 4'b0001;  //Store the contents of ACC in S
  reg [3:0] ADD = 4'b0010;  //ADD the contents of the ACC to contents of S
  reg [3:0] SUB = 4'b0011;  //SUB the contents of the ACC to contents of S
  reg [3:0] JMP = 4'b0100;  //Set PC := S
  reg [3:0] JGE = 4'b0101;  //If ACC >= 0, PC := S
  reg [3:0] JNE = 4'b0110;  //If ACC ~= 0, PC := S
  reg [3:0] STP = 4'b0111;  //Stop

  always @(posedge clk)
  begin
    if (reset == 1)
      state <= INIT;
    else
      state <= next_state;
  end

  always @(state or opcode)
  begin
    case (state)
      INIT:
        next_state = FETCH;
      FETCH:
        next_state = EXEC;
      EXEC:
        if (opcode == STP)
          next_state = EXEC;
        else
          next_state = FETCH;
      default: next_state = INIT;
    endcase
  end

  always @(state or opcode or reset) begin
    case (state)
      INIT: begin
        PCen  = 1;
        IRen  = 1;
        ACCen = 1;
        Wen = 0;
        Ren = 0;
      end
      FETCH: begin
        //Store contents of mem[PC] in IR
        //Increment the contents of the PC register
        IRen = 1;  //Enable the IR for a new entry
        PCen = 1;  //Enable the PC for a new entry
        ACCen = 0; //Disable the accumulator
        M = 2'b10; //Set ALU to increment on Xbus input (pc)
        Xsel = 0;  //place contents of PC on Xbus destined for ALU
        //Ysel Dont care
        Asel = 0;  //place contents of PC on Abus destined for mem
        Ren = 1;   //Enable memory for a read on next neg edge
        Wen = 0;
      end
      EXEC: begin
        if (opcode == LDA) begin
          IRen = 0; PCen = 0; ACCen = 1;
          M = 2'b00;
          Xsel = 0; Ysel = 1; Asel = 1;
          Ren = 1; Wen = 0;
        end
        else if (opcode == STO) begin
          IRen = 0; PCen = 0; ACCen = 0;
          Xsel = 1;           Asel = 1;
          Ren = 0; Wen = 1;
        end
        else if (opcode == ADD) begin
          IRen = 0; PCen = 0; ACCen = 1;
          M = 2'b01;
          Xsel = 1; Ysel = 1; Asel = 1;
          Ren = 1; Wen = 0;
        end
        else if (opcode == SUB) begin
          IRen = 0; PCen = 0; ACCen = 1;
          M = 2'b11;
          Xsel = 1; Ysel = 1; Asel = 1;
          Ren = 1; Wen = 0;
        end
        else if (opcode == JMP) begin
          IRen = 0; PCen = 1; ACCen = 0;
          M = 2'b00;
          Xsel = 0; Ysel = 0; 
          Ren = 0; Wen = 0;
        end
        else if (opcode == JGE) begin
          IRen = 0;
          PCen = ~acc[MAXWIDTH-1];
          //If ACC>=0 then acc[MAXWIDTH-1]=0
          //Otherwise do nothing by disabling the PC
          ACCen = 0;
          M = 2'b00;
          Xsel = 0; Ysel = 0;
          Ren = 0; Wen = 0;
        end
        else if (opcode == JNE) begin
          IRen = 0;
          //If the acc is non-zero, then at least one bit=1
          //Otherwise do nothing by disabling the PC
          PCen = |acc;
          ACCen = 0;
          M = 2'b00;
          Xsel = 0; Ysel = 0; 
          Ren = 0; Wen = 0;
        end
        else begin
          IRen = 0; PCen = 0; ACCen = 0;
          Xsel = 0;
          Ren = 0; Wen = 0;
        end
      end
      default: begin
      end
    endcase
  end

endmodule //mu0_controller

mu0/mem.v
/**
	project MU0
	module mem, simple non-synthesisable memory
	G. Borg
	Feb 2009
**/
`timescale 1 ns/1 ps
module mem (Clk, Wen, Ren, address, write_data, read_data);
`include "defs.h"
  input  Clk;
  input  Wen;
  input  Ren;
  input  [MAXDEPTH-1:0] address;
  input  [MAXWIDTH-1:0] write_data;
  output [MAXWIDTH-1:0] read_data;
  reg    [MAXWIDTH-1:0] read_data;
  reg    [MAXWIDTH-1:0] mem [12'h0:12'hFFF];

  initial 
    $readmemh("prog.lst", mem);

  always @(negedge Clk)
  begin
    if (Wen) 
      mem[address] <= write_data;
    if (Ren)
      read_data    <= mem[address];
  end

endmodule //mem.v

mu0/mu0.v
/**
	project MU0
	module mu0_ctrl, MU0 Controller
	G. Borg
	Feb 2009
**/
`timescale 1 ns/1 ps
module mu0(clk, reset, pc, ir, acc);
`include "defs.h"
  input clk, reset;
  wire Asel, Xsel, Ysel, ACCen, PCen, IRen, Ren, Wen;
  wire [1:0] M;
  output [MAXWIDTH-1:0] pc, ir, acc, Zbus;
  wire [MAXDEPTH-1:0] Abus;
  wire [MAXWIDTH-1:0] Xbus, Dbus;

  // Instruction and data memory (non-synthesizable)
  mem memory (
    .Clk(clk), .Wen(Wen), .Ren(Ren),
    .address(Abus), .write_data(Xbus), .read_data(Dbus));

  // Control unit
  mu0_controller control_unit (
    .clk(clk), .reset(reset), .opcode(ir[MAXWIDTH-1:MAXWIDTH-4]),
    .acc(acc), .Asel(Asel), .ACCen(ACCen), .PCen(PCen), .IRen(IRen),
    .M(M), .Xsel(Xsel), .Ysel(Ysel), .Ren(Ren), .Wen(Wen));

  // Datapath
  mu0_datapath datapath (
    .clk(clk), .reset(reset),
    .Abus(Abus), .Xbus(Xbus), .Dbus(Dbus), .acc(acc), .ir(ir), .pc(pc),
    .M(M), .PCen(PCen), .IRen(IRen), .ACCen(ACCen),
    .Xsel(Xsel), .Ysel(Ysel), .Asel(Asel));

endmodule //mu0

mu0/mu0_tb.v
/**
	project MU0
	module TB_mu0_ctrl, test bench for mu0_ctrl
	G. Borg
	Feb 2009
**/
`timescale 1 ns/1 ps

module mu0_tb;
`include "defs.h"
  reg clk, reset;
  wire [MAXWIDTH-1:0] pc;
  wire [MAXWIDTH-1:0] ir;
  wire [MAXWIDTH-1:0] acc;

  mu0 processor (
    .clk(clk), .reset(reset),
    .pc(pc), .ir(ir), .acc(acc)
  );

  // Test clock generation.
  //
  // Clock pulse starts from 0.
  initial
  begin
    clk = 1'b0;
    reset = 1'b1;
    #10 reset = 1'b0;
  end
  // Free-running clock
  always
    #5 clk = ~clk;

  // Write simulation data to a VCD waveform file.
  initial
  begin
    // Open a VCD file for writing
    $dumpfile("mu0.vcd");
    // Dump the values of all nets and wires in module "gcd_main", seen
    // from hierarchy level 0
    $dumpvars(0, mu0_tb);
  end

  initial 
  begin
    #1000; 
    $finish;
  end

endmodule

mu0/mu0_structural.vcd
$date
	Sat Feb 27 22:31:49 2016
$end
$version
	Icarus Verilog
$end
$timescale
	1ps
$end
$scope module mu0_tb $end
$var wire 16 ! acc [15:0] $end
$var wire 16 " ir [15:0] $end
$var wire 16 # pc [15:0] $end
$var reg 1 $ clk $end
$var reg 1 % reset $end
$scope module processor $end
$var wire 1 & ACCen $end
$var wire 12 ' Abus [11:0] $end
$var wire 1 ( Asel $end
$var wire 16 ) Dbus [15:0] $end
$var wire 1 * IRen $end
$var wire 2 + M [1:0] $end
$var wire 1 , PCen $end
$var wire 1 - Ren $end
$var wire 1 . Wen $end
$var wire 16 / Xbus [15:0] $end
$var wire 1 0 Xsel $end
$var wire 1 1 Ysel $end
$var wire 16 2 Zbus [15:0] $end
$var wire 16 3 acc [15:0] $end
$var wire 1 4 clk $end
$var wire 16 5 ir [15:0] $end
$var wire 16 6 pc [15:0] $end
$var wire 1 7 reset $end
$scope module memory $end
$var wire 1 4 Clk $end
$var wire 1 - Ren $end
$var wire 1 . Wen $end
$var wire 12 8 address [11:0] $end
$var wire 16 9 write_data [15:0] $end
$var reg 16 : read_data [15:0] $end
$upscope $end
$scope module control_unit $end
$var wire 16 ; acc [15:0] $end
$var wire 1 4 clk $end
$var wire 4 < opcode [3:0] $end
$var wire 1 7 reset $end
$var reg 1 = ACCen $end
$var reg 4 > ADD [3:0] $end
$var reg 1 ? Asel $end
$var reg 1 @ IRen $end
$var reg 4 A JGE [3:0] $end
$var reg 4 B JMP [3:0] $end
$var reg 4 C JNE [3:0] $end
$var reg 4 D LDA [3:0] $end
$var reg 2 E M [1:0] $end
$var reg 1 F PCen $end
$var reg 1 G Ren $end
$var reg 4 H STO [3:0] $end
$var reg 4 I STP [3:0] $end
$var reg 4 J SUB [3:0] $end
$var reg 1 K Wen $end
$var reg 1 L Xsel $end
$var reg 1 M Ysel $end
$var reg 2 N next_state [1:0] $end
$var reg 2 O state [1:0] $end
$upscope $end
$scope module datapath $end
$var wire 1 & ACCen $end
$var wire 12 P Abus [11:0] $end
$var wire 1 ( Asel $end
$var wire 16 Q Dbus [15:0] $end
$var wire 1 * IRen $end
$var wire 2 R M [1:0] $end
$var wire 1 , PCen $end
$var wire 16 S Xbus [15:0] $end
$var wire 1 0 Xsel $end
$var wire 16 T Ybus [15:0] $end
$var wire 1 1 Ysel $end
$var wire 16 U Zbus [15:0] $end
$var wire 16 V acc [15:0] $end
$var wire 1 4 clk $end
$var wire 16 W ir [15:0] $end
$var wire 16 X pc [15:0] $end
$var wire 1 7 reset $end
$scope module alu $end
$var wire 2 Y M [1:0] $end
$var wire 16 Z X [15:0] $end
$var wire 16 [ Y [15:0] $end
$var reg 16 \ Z [15:0] $end
$upscope $end
$scope module x_mux $end
$var wire 16 ] a [15:0] $end
$var wire 16 ^ b [15:0] $end
$var wire 1 0 s $end
$var wire 16 _ z [15:0] $end
$upscope $end
$scope module y_mux $end
$var wire 16 ` a [15:0] $end
$var wire 16 a b [15:0] $end
$var wire 1 1 s $end
$var wire 16 b z [15:0] $end
$upscope $end
$scope module a_mux $end
$var wire 12 c a [11:0] $end
$var wire 12 d b [11:0] $end
$var wire 1 ( s $end
$var wire 12 e z [11:0] $end
$upscope $end
$scope module ProgramCounter $end
$var wire 1 4 clk $end
$var wire 16 f d [15:0] $end
$var wire 1 , en $end
$var wire 1 7 rs $end
$var reg 16 g q [15:0] $end
$upscope $end
$scope module InstructionRegister $end
$var wire 1 4 clk $end
$var wire 16 h d [15:0] $end
$var wire 1 * en $end
$var wire 1 7 rs $end
$var reg 16 i q [15:0] $end
$upscope $end
$scope module Accumulator $end
$var wire 1 4 clk $end
$var wire 16 j d [15:0] $end
$var wire 1 & en $end
$var wire 1 7 rs $end
$var reg 16 k q [15:0] $end
$upscope $end
$upscope $end
$upscope $end
$upscope $end
$enddefinitions $end
#0
$dumpvars
bx k
b0 j
bx i
bx h
bx g
b0 f
bx e
bx d
bx c
bx b
bx a
bx `
bx _
bx ^
bx ]
b0 \
bx [
bx Z
bx Y
bx X
bx W
bx V
b0 U
bx T
bx S
bx R
bx Q
bx P
bx O
b0 N
xM
xL
xK
b11 J
b111 I
b1 H
xG
xF
bx E
b0 D
b110 C
b100 B
b101 A
x@
x?
b10 >
x=
bx <
bx ;
bx :
bx 9
bx 8
17
bx 6
bx 5
04
bx 3
bz 2
x1
x0
bx /
x.
x-
x,
bx +
x*
bx )
x(
bx '
x&
1%
0$
bx #
bx "
bx !
$end
#5000
0G
0-
0K
0.
1=
1&
1@
1*
1F
1,
b1 N
b0 O
1$
14
#10000
0$
04
0%
07
#15000
b0 '
b0 8
b0 P
b0 e
b1 \
b1 U
b1 f
b1 j
b0 /
b0 9
b0 S
b0 Z
b0 _
b0 c
1G
1-
0?
0(
0L
00
b10 E
b10 +
b10 R
b10 Y
0=
0&
b10 N
b0 k
b0 !
b0 3
b0 ;
b0 V
b0 ^
b0 g
b0 #
b0 6
b0 X
b0 ]
b1 O
1$
14
#20000
b100 :
b100 )
b100 Q
b100 a
b100 h
0$
04
#25000
b100 '
b100 8
b100 P
b100 e
b100 \
b100 U
b100 f
b100 j
1?
1(
1M
11
b0 E
b0 +
b0 R
b0 Y
1=
1&
0F
0,
0@
0*
b1 N
b1 /
b1 9
b1 S
b1 Z
b1 _
b1 c
b100 T
b100 [
b100 b
b100 d
b0 <
b10 O
b1 g
b1 #
b1 6
b1 X
b1 ]
b100 i
b100 "
b100 5
b100 W
b100 `
1$
14
#30000
b1010 \
b1010 U
b1010 f
b1010 j
b1010 T
b1010 [
b1010 b
b1010 :
b1010 )
b1010 Q
b1010 a
b1010 h
0$
04
#35000
b1 '
b1 8
b1 P
b1 e
b10 \
b10 U
b10 f
b10 j
0?
0(
b10 E
b10 +
b10 R
b10 Y
0=
0&
1F
1,
1@
1*
b10 N
b1010 k
b1010 !
b1010 3
b1010 ;
b1010 V
b1010 ^
b1 O
1$
14
#40000
b10000000000101 T
b10000000000101 [
b10000000000101 b
b10000000000101 :
b10000000000101 )
b10000000000101 Q
b10000000000101 a
b10000000000101 h
0$
04
#45000
b10000000001111 \
b10000000001111 U
b10000000001111 f
b10000000001111 j
b101 '
b101 8
b101 P
b101 e
1?
1(
1L
10
b1 E
b1 +
b1 R
b1 Y
1=
1&
0F
0,
0@
0*
b1 N
b1010 /
b1010 9
b1010 S
b1010 Z
b1010 _
b10 c
b101 d
b10 <
b10 O
b10 g
b10 #
b10 6
b10 X
b10 ]
b10000000000101 i
b10000000000101 "
b10000000000101 5
b10000000000101 W
b10000000000101 `
1$
14
#50000
b1011 \
b1011 U
b1011 f
b1011 j
b1 T
b1 [
b1 b
b1 :
b1 )
b1 Q
b1 a
b1 h
0$
04
#55000
b10 '
b10 8
b10 P
b10 e
b11 \
b11 U
b11 f
b11 j
b10 /
b10 9
b10 S
b10 Z
b10 _
0?
0(
0L
00
b10 E
b10 +
b10 R
b10 Y
0=
0&
1F
1,
1@
1*
b10 N
b1011 k
b1011 !
b1011 3
b1011 ;
b1011 V
b1011 ^
b1 O
1$
14
#60000
b1000000000110 T
b1000000000110 [
b1000000000110 b
b1000000000110 :
b1000000000110 )
b1000000000110 Q
b1000000000110 a
b1000000000110 h
0$
04
#65000
b1100 \
b1100 U
b1100 f
b1100 j
b110 '
b110 8
b110 P
b110 e
1K
1.
0G
0-
1?
1(
1L
10
0F
0,
0@
0*
b1 N
b1011 /
b1011 9
b1011 S
b1011 Z
b1011 _
b11 c
b110 d
b1 <
b10 O
b11 g
b11 #
b11 6
b11 X
b11 ]
b1000000000110 i
b1000000000110 "
b1000000000110 5
b1000000000110 W
b1000000000110 `
1$
14
#70000
0$
04
#75000
b100 \
b100 U
b100 f
b100 j
b11 '
b11 8
b11 P
b11 e
b11 /
b11 9
b11 S
b11 Z
b11 _
0K
0.
1G
1-
0?
0(
0L
00
1F
1,
1@
1*
b10 N
b1 O
1$
14
#80000
b111000000000000 T
b111000000000000 [
b111000000000000 b
b111000000000000 :
b111000000000000 )
b111000000000000 Q
b111000000000000 a
b111000000000000 h
0$
04
#85000
b101 \
b101 U
b101 f
b101 j
b100 '
b100 8
b100 P
b100 e
0G
0-
0F
0,
0@
0*
b100 /
b100 9
b100 S
b100 Z
b100 _
b100 c
b0 d
b111 <
b10 O
b100 g
b100 #
b100 6
b100 X
b100 ]
b111000000000000 i
b111000000000000 "
b111000000000000 5
b111000000000000 W
b111000000000000 `
1$
14
