bcd/bcd.v
module bcd (clk, reset, count);
  input clk, reset;
  output [3:0] count;
  reg [3:0] count;
  reg [3:0] current_state;
  reg [3:0] next_state;
  parameter ZERO = 4'b0000, ONE = 4'b0001, TWO = 4'b0010, THREE = 4'b0011,
            FOUR = 4'b0100, FIVE = 4'b0101, SIX = 4'b0110, SEVEN = 4'b0111,
            EIGHT = 4'b1000, NINE = 4'b1001;

  always @(posedge clk or posedge reset)
  begin
    if (reset) 
      current_state <= ZERO;
    else 
      current_state <= next_state;
  end

  always @(current_state)
  begin
    case (current_state)
      ZERO: begin
        count = ZERO;  
        next_state = ONE;
      end
      ONE: begin
        count = ONE;   
        next_state = TWO;
      end
      TWO: begin
        count = TWO;   
        next_state = THREE;
      end
      THREE: begin
        count = THREE;   
        next_state = FOUR;
      end
      FOUR: begin
        count = FOUR;  
        next_state = FIVE;
      end
      FIVE: begin
        count = FIVE;  
        next_state = SIX;
      end
      SIX: begin
        count = SIX;   
        next_state = SEVEN;
      end
      SEVEN: begin
        count = SEVEN; 
        next_state = EIGHT;
      end
      EIGHT: begin
        count = EIGHT; 
        next_state = NINE;
      end
      NINE: begin
        count = NINE;  
        next_state = ZERO;
      end
      default: begin 
        count = 4'b1111; 
        next_state = ZERO;
      end
    endcase
  end
endmodule

bcd/bcd_tb.v
`timescale 1 ns / 1 ns

module main;
  reg clk, reset;
  wire [3:0] count;

  bcd test(.clk(clk), .reset(reset), .count(count));

  // Test clock generation.
  //
  // Clock pulse starts from 0.
  initial 
    clk = 1'b0;
  // Free-running clock  
  always
    #25 clk = ~clk;
    
  initial 
  begin
    reset = 1'b1;
    #50 reset = 1'b0;
    #600
    $finish;
  end

  // Write simulation data to a Value Change Dump (VCD) file.
  // More on this in lecture 07, scheduled next week!
  initial 
  begin
    // Open a VCD file for writing
    $dumpfile("bcd.vcd");
    // Dump the values of all nets and wires in module "main", since simulation 
    // time 0
    $dumpvars(0, main);
  end

endmodule

bcd/bcd.vcd
$date
	Sat Feb 27 22:31:49 2016
$end
$version
	Icarus Verilog
$end
$timescale
	1ns
$end
$scope module main $end
$var wire 4 ! count [3:0] $end
$var reg 1 " clk $end
$var reg 1 # reset $end
$scope module test $end
$var wire 1 $ clk $end
$var wire 1 % reset $end
$var reg 4 & count [3:0] $end
$var reg 4 ' current_state [3:0] $end
$var reg 4 ( next_state [3:0] $end
$upscope $end
$upscope $end
$enddefinitions $end
#0
$dumpvars
b1 (
b0 '
b0 &
1%
0$
1#
0"
b0 !
$end
#25
1"
1$
#50
0"
0$
0#
0%
#75
b10 (
b1 &
b1 !
b1 '
1"
1$
#100
0"
0$
#125
b11 (
b10 &
b10 !
b10 '
1"
1$
#150
0"
0$
#175
b100 (
b11 &
b11 !
b11 '
1"
1$
#200
0"
0$
#225
b101 (
b100 &
b100 !
b100 '
1"
1$
#250
0"
0$
#275
b110 (
b101 &
b101 !
b101 '
1"
1$
#300
0"
0$
#325
b111 (
b110 &
b110 !
b110 '
1"
1$
#350
0"
0$
#375
b1000 (
b111 &
b111 !
b111 '
1"
1$
#400
0"
0$
#425
b1001 (
b1000 &
b1000 !
b1000 '
1"
1$
#450
0"
0$
#475
b0 (
b1001 &
b1001 !
b1001 '
1"
1$
#500
0"
0$
#525
b1 (
b0 &
b0 !
b0 '
1"
1$
#550
0"
0$
#575
b10 (
b1 &
b1 !
b1 '
1"
1$
#600
0"
0$
#625
b11 (
b10 &
b10 !
b10 '
1"
1$
