gcd/gcd.v
module gcd (
  clock, reset, start,
  a, b,
  outp, done);
  parameter WIDTH = 8;
  parameter s0 = 2'b00, s1 = 2'b01, s2 = 2'b10, s3 = 2'b11;
  input clock, reset, start;
  input [WIDTH-1:0] a, b;
  output [WIDTH-1:0] outp;
  output done;
  reg done;
  reg [WIDTH-1:0] outp;
  reg[1:0] state;
  reg [WIDTH-1:0] x_reg, x_next, y_reg, y_next;
  
  always @(posedge clock or posedge reset)
  begin
    done = 1'b0;
    if (reset) begin
      state = s0;
      x_reg = 0;
      y_reg = 0;
      done = 1'b0;
      outp = 0;
    end
    else begin
      x_reg = x_next;
      y_reg = y_next;
      case (state)
        s0: begin
          if (start) begin
            x_next = a;
            y_next = b;
            state = s1;
          end
          else
            state = s0;
        end
        s1: begin
          if (x_reg != 0 && y_reg != 0)
            state = s2;
          else begin
            outp = 0;
            state = s3;
          end
        end
        s2: begin
          if (x_reg > y_reg) begin
            x_next = x_reg - y_reg;
            state = s2;
          end
          else if (x_reg < y_reg) begin
            y_next = y_reg - x_reg;
            state = s2;
          end
          else
            state = s3;
        end
        s3: begin
          done = 1'b1;
          outp = x_reg;
          state = s0;
        end
      endcase
    end
  end

endmodule

gcd/gcd_tb.v
`timescale 1 ns / 10 ps

module gcd_main;
  parameter WIDTH = 8;
  reg clock, reset, start;
  reg [WIDTH-1:0] a, b, y, y_ref;
  reg [WIDTH-1:0] a_reg, b_reg;
  wire [WIDTH-1:0] outp;
  wire done;
  // 
  parameter GCD_tests = 8;
  integer N,M;
  reg Passed, FailTime;
  integer SimResults;
  // Declare memory array for test data
  reg [WIDTH-1:0] ab_y_ref_arr[1:GCD_tests*3];
  // Profiling counter
  integer ncycles;
  
  // Test the GCD implementation
  gcd test(
    .clock(clock), .reset(reset), .start(start),
    .a(a), .b(b),
    .outp(outp), .done(done)
  );  
  
  // Test clock generation.
  //
  // Clock pulse starts from 0.
  initial 
    clock = 1'b0;
  // Free-running clock  
  always
    #25 clock = ~clock;  
  
  // PROFILING
  always @(posedge clock or posedge reset)
  begin
    if (reset)
      ncycles = 0;
    else
      ncycles = ncycles + 1;
  end
  
  // Test GCD algorithm
  initial
  begin
    // Load contents of "gcd_test_data_hex.txt" into array.
    $readmemh("gcd_test_data_hex.txt", ab_y_ref_arr);
    // Open simulation results file.
    SimResults = $fopen("gcd_alg_test_results.txt");
    Passed = 1; // Set to 0 if fails
    for (N = 0; N < GCD_tests; N = N + 1)
    begin
      a = ab_y_ref_arr[(N*3)+1];
      b = ab_y_ref_arr[(N*3)+2];
      y_ref = ab_y_ref_arr[(N*3)+3];
      ///////////////////////////////////////////////////
      reset = 1;
      #50 reset = 0; start = 1;
      ///////////////////////////////////////////////////
      wait (done);
      #50;
      // Diagnostics for GCD algorithm
      if (outp != y_ref) begin
        Passed = 0;
        $fdisplay(SimResults, "GCD Error: A=%d, B=%d, Y=%d. Y should be %d",
        a, b, outp, y_ref);
      end
      else begin
        $fdisplay(SimResults, "GCD OK: Number of cycles = %d", ncycles);
      end
    end
    if (Passed == 1) begin
      $fdisplay(SimResults, "GCD algorithm test has passed");
      $fclose(SimResults);
      $finish;
    end
  end

  // Write simulation data to a VCD waveform file.
  initial 
  begin
    // Open a VCD file for writing
    $dumpfile("gcd.vcd");
    // Dump the values of all nets and wires in module "gcd_main", seen 
    // from hierarchy level 0
    $dumpvars(0, gcd_main);
  end

endmodule

gcd/gcd.vcd
$date
	Sat Feb 27 22:31:49 2016
$end
$version
	Icarus Verilog
$end
$timescale
	10ps
$end
$scope module gcd_main $end
$var wire 1 ! done $end
$var wire 8 " outp [7:0] $end
$var integer 32 # N [31:0] $end
$var reg 1 $ Passed $end
$var integer 32 % SimResults [31:0] $end
$var reg 8 & a [7:0] $end
$var reg 8 ' b [7:0] $end
$var reg 1 ( clock $end
$var integer 32 ) ncycles [31:0] $end
$var reg 1 * reset $end
$var reg 1 + start $end
$var reg 8 , y_ref [7:0] $end
$scope module test $end
$var wire 8 - a [7:0] $end
$var wire 8 . b [7:0] $end
$var wire 1 / clock $end
$var wire 1 0 reset $end
$var wire 1 1 start $end
$var reg 1 2 done $end
$var reg 8 3 outp [7:0] $end
$var reg 2 4 state [1:0] $end
$var reg 8 5 x_next [7:0] $end
$var reg 8 6 x_reg [7:0] $end
$var reg 8 7 y_next [7:0] $end
$var reg 8 8 y_reg [7:0] $end
$upscope $end
$upscope $end
$enddefinitions $end
#0
$dumpvars
b0 8
bx 7
b0 6
bx 5
b0 4
b0 3
02
x1
10
0/
b110001 .
b10101 -
b111 ,
x+
1*
b0 )
0(
b110001 '
b10101 &
b10 %
1$
b0 #
b0 "
0!
$end
#2500
1(
1/
#5000
0(
0/
1+
11
0*
00
#7500
b1 4
b110001 7
b10101 5
bx 8
bx 6
b1 )
1(
1/
#10000
0(
0/
#12500
b10 )
b10 4
b110001 8
b10101 6
1(
1/
#15000
0(
0/
#17500
b11100 7
b11 )
1(
1/
#20000
0(
0/
#22500
b100 )
b111 7
b11100 8
1(
1/
#25000
0(
0/
#27500
b1110 5
b111 8
b101 )
1(
1/
#30000
0(
0/
#32500
b110 )
b111 5
b1110 6
1(
1/
#35000
0(
0/
#37500
b11 4
b111 6
b111 )
1(
1/
#40000
0(
0/
#42500
b1000 )
b0 4
b111 3
b111 "
12
1!
1(
1/
#45000
0(
0/
#47500
b0 3
b0 "
b0 8
b0 6
02
0!
b0 )
1(
1/
1*
10
b101 ,
b11110 '
b11110 .
b11001 &
b11001 -
b1 #
#50000
0(
0/
#52500
b1 )
b1 4
b11110 7
b11001 5
b111 8
b111 6
1(
1/
0*
00
#55000
0(
0/
#57500
b10 4
b11110 8
b11001 6
b10 )
1(
1/
#60000
0(
0/
#62500
b11 )
b101 7
1(
1/
#65000
0(
0/
#67500
b10100 5
b101 8
b100 )
1(
1/
#70000
0(
0/
#72500
b101 )
b1111 5
b10100 6
1(
1/
#75000
0(
0/
#77500
b1010 5
b1111 6
b110 )
1(
1/
#80000
0(
0/
#82500
b111 )
b101 5
b1010 6
1(
1/
#85000
0(
0/
#87500
b11 4
b101 6
b1000 )
1(
1/
#90000
0(
0/
#92500
b1001 )
b0 4
b101 3
b101 "
12
1!
1(
1/
#95000
0(
0/
#97500
b0 3
b0 "
b0 8
b0 6
02
0!
b0 )
1(
1/
1*
10
b1 ,
b11011 '
b11011 .
b10011 &
b10011 -
b10 #
#100000
0(
0/
#102500
b1 )
b1 4
b11011 7
b10011 5
b101 8
b101 6
1(
1/
0*
00
#105000
0(
0/
#107500
b10 4
b11011 8
b10011 6
b10 )
1(
1/
#110000
0(
0/
#112500
b11 )
b1000 7
1(
1/
#115000
0(
0/
#117500
b1011 5
b1000 8
b100 )
1(
1/
#120000
0(
0/
#122500
b101 )
b11 5
b1011 6
1(
1/
#125000
0(
0/
#127500
b101 7
b11 6
b110 )
1(
1/
#130000
0(
0/
#132500
b111 )
b10 7
b101 8
1(
1/
#135000
0(
0/
#137500
b1 5
b10 8
b1000 )
1(
1/
#140000
0(
0/
#142500
b1001 )
b1 7
b1 6
1(
1/
#145000
0(
0/
#147500
b11 4
b1 8
b1010 )
1(
1/
#150000
0(
0/
#152500
b1011 )
b0 4
b1 3
b1 "
12
1!
1(
1/
#155000
0(
0/
#157500
b0 3
b0 "
b0 8
b0 6
02
0!
b0 )
1(
1/
1*
10
b101000 ,
b101000 '
b101000 .
b101000 &
b101000 -
b11 #
#160000
0(
0/
#162500
b1 )
b1 4
b101000 7
b101000 5
b1 8
b1 6
1(
1/
0*
00
#165000
0(
0/
#167500
b10 4
b101000 8
b101000 6
b10 )
1(
1/
#170000
0(
0/
#172500
b11 )
b11 4
1(
1/
#175000
0(
0/
#177500
b0 4
b101000 3
b101000 "
12
1!
b100 )
1(
1/
#180000
0(
0/
#182500
b0 )
b0 3
b0 "
b0 8
b0 6
02
0!
1(
1/
1*
10
b1010 ,
b1101110 '
b1101110 .
b11111010 &
b11111010 -
b100 #
#185000
0(
0/
#187500
b1 4
b1101110 7
b11111010 5
b101000 8
b101000 6
b1 )
1(
1/
0*
00
#190000
0(
0/
#192500
b10 )
b10 4
b1101110 8
b11111010 6
1(
1/
#195000
0(
0/
#197500
b10001100 5
b11 )
1(
1/
#200000
0(
0/
#202500
b100 )
b11110 5
b10001100 6
1(
1/
#205000
0(
0/
#207500
b1010000 7
b11110 6
b101 )
1(
1/
#210000
0(
0/
#212500
b110 )
b110010 7
b1010000 8
1(
1/
#215000
0(
0/
#217500
b10100 7
b110010 8
b111 )
1(
1/
#220000
0(
0/
#222500
b1000 )
b1010 5
b10100 8
1(
1/
#225000
0(
0/
#227500
b1010 7
b1010 6
b1001 )
1(
1/
#230000
0(
0/
#232500
b1010 )
b11 4
b1010 8
1(
1/
#235000
0(
0/
#237500
b0 4
b1010 3
b1010 "
12
1!
b1011 )
1(
1/
#240000
0(
0/
#242500
b0 )
b0 3
b0 "
b0 8
b0 6
02
0!
1(
1/
1*
10
b101 ,
b11111010 '
b11111010 .
b101 &
b101 -
b101 #
#245000
0(
0/
#247500
b1 4
b11111010 7
b101 5
b1010 8
b1010 6
b1 )
1(
1/
0*
00
#250000
0(
0/
#252500
b10 )
b10 4
b11111010 8
b101 6
1(
1/
#255000
0(
0/
#257500
b11110101 7
b11 )
1(
1/
#260000
0(
0/
#262500
b100 )
b11110000 7
b11110101 8
1(
1/
#265000
0(
0/
#267500
b11101011 7
b11110000 8
b101 )
1(
1/
#270000
0(
0/
#272500
b110 )
b11100110 7
b11101011 8
1(
1/
#275000
0(
0/
#277500
b11100001 7
b11100110 8
b111 )
1(
1/
#280000
0(
0/
#282500
b1000 )
b11011100 7
b11100001 8
1(
1/
#285000
0(
0/
#287500
b11010111 7
b11011100 8
b1001 )
1(
1/
#290000
0(
0/
#292500
b1010 )
b11010010 7
b11010111 8
1(
1/
#295000
0(
0/
#297500
b11001101 7
b11010010 8
b1011 )
1(
1/
#300000
0(
0/
#302500
b1100 )
b11001000 7
b11001101 8
1(
1/
#305000
0(
0/
#307500
b11000011 7
b11001000 8
b1101 )
1(
1/
#310000
0(
0/
#312500
b1110 )
b10111110 7
b11000011 8
1(
1/
#315000
0(
0/
#317500
b10111001 7
b10111110 8
b1111 )
1(
1/
#320000
0(
0/
#322500
b10000 )
b10110100 7
b10111001 8
1(
1/
#325000
0(
0/
#327500
b10101111 7
b10110100 8
b10001 )
1(
1/
#330000
0(
0/
#332500
b10010 )
b10101010 7
b10101111 8
1(
1/
#335000
0(
0/
#337500
b10100101 7
b10101010 8
b10011 )
1(
1/
#340000
0(
0/
#342500
b10100 )
b10100000 7
b10100101 8
1(
1/
#345000
0(
0/
#347500
b10011011 7
b10100000 8
b10101 )
1(
1/
#350000
0(
0/
#352500
b10110 )
b10010110 7
b10011011 8
1(
1/
#355000
0(
0/
#357500
b10010001 7
b10010110 8
b10111 )
1(
1/
#360000
0(
0/
#362500
b11000 )
b10001100 7
b10010001 8
1(
1/
#365000
0(
0/
#367500
b10000111 7
b10001100 8
b11001 )
1(
1/
#370000
0(
0/
#372500
b11010 )
b10000010 7
b10000111 8
1(
1/
#375000
0(
0/
#377500
b1111101 7
b10000010 8
b11011 )
1(
1/
#380000
0(
0/
#382500
b11100 )
b1111000 7
b1111101 8
1(
1/
#385000
0(
0/
#387500
b1110011 7
b1111000 8
b11101 )
1(
1/
#390000
0(
0/
#392500
b11110 )
b1101110 7
b1110011 8
1(
1/
#395000
0(
0/
#397500
b1101001 7
b1101110 8
b11111 )
1(
1/
#400000
0(
0/
#402500
b100000 )
b1100100 7
b1101001 8
1(
1/
#405000
0(
0/
#407500
b1011111 7
b1100100 8
b100001 )
1(
1/
#410000
0(
0/
#412500
b100010 )
b1011010 7
b1011111 8
1(
1/
#415000
0(
0/
#417500
b1010101 7
b1011010 8
b100011 )
1(
1/
#420000
0(
0/
#422500
b100100 )
b1010000 7
b1010101 8
1(
1/
#425000
0(
0/
#427500
b1001011 7
b1010000 8
b100101 )
1(
1/
#430000
0(
0/
#432500
b100110 )
b1000110 7
b1001011 8
1(
1/
#435000
0(
0/
#437500
b1000001 7
b1000110 8
b100111 )
1(
1/
#440000
0(
0/
#442500
b101000 )
b111100 7
b1000001 8
1(
1/
#445000
0(
0/
#447500
b110111 7
b111100 8
b101001 )
1(
1/
#450000
0(
0/
#452500
b101010 )
b110010 7
b110111 8
1(
1/
#455000
0(
0/
#457500
b101101 7
b110010 8
b101011 )
1(
1/
#460000
0(
0/
#462500
b101100 )
b101000 7
b101101 8
1(
1/
#465000
0(
0/
#467500
b100011 7
b101000 8
b101101 )
1(
1/
#470000
0(
0/
#472500
b101110 )
b11110 7
b100011 8
1(
1/
#475000
0(
0/
#477500
b11001 7
b11110 8
b101111 )
1(
1/
#480000
0(
0/
#482500
b110000 )
b10100 7
b11001 8
1(
1/
#485000
0(
0/
#487500
b1111 7
b10100 8
b110001 )
1(
1/
#490000
0(
0/
#492500
b110010 )
b1010 7
b1111 8
1(
1/
#495000
0(
0/
#497500
b101 7
b1010 8
b110011 )
1(
1/
#500000
0(
0/
#502500
b110100 )
b11 4
b101 8
1(
1/
#505000
0(
0/
#507500
b0 4
b101 3
b101 "
12
1!
b110101 )
1(
1/
#510000
0(
0/
#512500
b0 )
b0 3
b0 "
b0 8
b0 6
02
0!
1(
1/
1*
10
b1 ,
b1 '
b1 .
b1 &
b1 -
b110 #
#515000
0(
0/
#517500
b1 4
b1 7
b1 5
b101 8
b101 6
b1 )
1(
1/
0*
00
#520000
0(
0/
#522500
b10 )
b10 4
b1 8
b1 6
1(
1/
#525000
0(
0/
#527500
b11 4
b11 )
1(
1/
#530000
0(
0/
#532500
b100 )
b0 4
b1 3
b1 "
12
1!
1(
1/
#535000
0(
0/
#537500
b0 3
b0 "
b0 8
b0 6
02
0!
b0 )
1(
1/
1*
10
b0 ,
b0 '
b0 .
b0 &
b0 -
b111 #
#540000
0(
0/
#542500
b1 )
b1 4
b0 7
b0 5
b1 8
b1 6
1(
1/
0*
00
#545000
0(
0/
#547500
b11 4
b0 8
b0 6
b10 )
1(
1/
#550000
0(
0/
#552500
b11 )
b0 4
12
1!
1(
1/
#555000
0(
0/
#557500
b1 4
02
0!
b100 )
1(
1/
b1000 #
