rom16x8/rom16x8.v
module rom16x8 (clk, re, addr, data); 
  input  clk; 
  input  re; 
  input  [3:0] addr; 
  output [7:0] data; 
  reg [7:0] ROM [15:0]; 
  reg [7:0] data;

  initial 
  begin
    ROM[ 0] = 8'h01; ROM[ 1] = 8'h02; ROM[ 2] = 8'h04; ROM[ 3] = 8'h08;
    ROM[ 4] = 8'h10; ROM[ 5] = 8'h20; ROM[ 6] = 8'h40; ROM[ 7] = 8'h80;
    ROM[ 8] = 8'h01; ROM[ 9] = 8'h03; ROM[10] = 8'h07; ROM[11] = 8'h0F;
    ROM[12] = 8'h1F; ROM[13] = 8'h3F; ROM[14] = 8'h7F; ROM[15] = 8'hFF;
  end

  always @(posedge clk) 
  begin 
    if (re) 
      data <= ROM[addr];
  end
   
endmodule

rom16x8/rom16x8_tb.v
`timescale 1 ns / 10 ps

module main;
  reg clk, re;
  reg [3:0] addr;
  wire [7:0] data;
  integer idx;
  
  rom16x8 uut(.clk(clk), .re(re), .addr(addr), .data(data));
  
  // Test clock generation.
  //
  // Clock pulse starts from 1.
  initial 
    clk = 1'b1;
  // Free-running clock  
  always
    #25 clk = ~clk;
    
  // Data stimulus
  initial 
  begin
    #1 re = 1'b0; addr = 4'h2;
    //
    for (idx = 0; idx <= 15; idx = idx + 1) 
    begin
      #50 addr = idx; re = 1'b1;      
    end
    #50
//    $stop;    // for Modelsim
    $finish;  // for Icarus Verilog 
  end
  
  initial
    $monitor("%t: clk = %b, re=%b, addr=%h, data=%h", $time, clk, re, addr, data);

  // Write simulation data to a Value Change Dump (VCD) file.
  initial 
  begin
    // Open a VCD file for writing
    $dumpfile("rom16x8.vcd");
    // Dump the values of all nets and wires in module "main", since simulation 
    // time 0
    $dumpvars(0, main);
  end

endmodule

rom16x8/rom16x8.vcd
$date
	Sat Feb 27 22:31:50 2016
$end
$version
	Icarus Verilog
$end
$timescale
	10ps
$end
$scope module main $end
$var wire 8 ! data [7:0] $end
$var reg 4 " addr [3:0] $end
$var reg 1 # clk $end
$var integer 32 $ idx [31:0] $end
$var reg 1 % re $end
$scope module uut $end
$var wire 4 & addr [3:0] $end
$var wire 1 ' clk $end
$var wire 1 ( re $end
$var reg 8 ) data [7:0] $end
$upscope $end
$upscope $end
$enddefinitions $end
#0
$dumpvars
bx )
x(
1'
bx &
x%
bx $
1#
bx "
bx !
$end
#100
b0 $
b10 "
b10 &
0%
0(
#2500
0#
0'
#5000
1#
1'
#5100
b1 $
1%
1(
b0 "
b0 &
#7500
0#
0'
#10000
b1 )
b1 !
1#
1'
#10100
b10 $
b1 "
b1 &
#12500
0#
0'
#15000
b10 )
b10 !
1#
1'
#15100
b11 $
b10 "
b10 &
#17500
0#
0'
#20000
b100 )
b100 !
1#
1'
#20100
b100 $
b11 "
b11 &
#22500
0#
0'
#25000
b1000 )
b1000 !
1#
1'
#25100
b101 $
b100 "
b100 &
#27500
0#
0'
#30000
b10000 )
b10000 !
1#
1'
#30100
b110 $
b101 "
b101 &
#32500
0#
0'
#35000
b100000 )
b100000 !
1#
1'
#35100
b111 $
b110 "
b110 &
#37500
0#
0'
#40000
b1000000 )
b1000000 !
1#
1'
#40100
b1000 $
b111 "
b111 &
#42500
0#
0'
#45000
b10000000 )
b10000000 !
1#
1'
#45100
b1001 $
b1000 "
b1000 &
#47500
0#
0'
#50000
b1 )
b1 !
1#
1'
#50100
b1010 $
b1001 "
b1001 &
#52500
0#
0'
#55000
b11 )
b11 !
1#
1'
#55100
b1011 $
b1010 "
b1010 &
#57500
0#
0'
#60000
b111 )
b111 !
1#
1'
#60100
b1100 $
b1011 "
b1011 &
#62500
0#
0'
#65000
b1111 )
b1111 !
1#
1'
#65100
b1101 $
b1100 "
b1100 &
#67500
0#
0'
#70000
b11111 )
b11111 !
1#
1'
#70100
b1110 $
b1101 "
b1101 &
#72500
0#
0'
#75000
b111111 )
b111111 !
1#
1'
#75100
b1111 $
b1110 "
b1110 &
#77500
0#
0'
#80000
b1111111 )
b1111111 !
1#
1'
#80100
b10000 $
b1111 "
b1111 &
#82500
0#
0'
#85000
b11111111 )
b11111111 !
1#
1'
